psd_tools-1.12.0.dist-info/RECORD
psd_tools-1.12.0.dist-info/WHEEL
psd_tools-1.12.0.dist-info/entry_points.txt
psd_tools-1.12.0.dist-info/top_level.txt
psd_tools-1.12.0.dist-info/METADATA
psd_tools-1.12.0.dist-info/licenses/LICENSE
psd_tools/version.py
psd_tools/registry.py
psd_tools/validators.py
psd_tools/constants.py
psd_tools/__init__.py
psd_tools/utils.py
psd_tools/py.typed
psd_tools/terminology.py
psd_tools/__main__.py
psd_tools/psd/descriptor.py
psd_tools/psd/image_data.py
psd_tools/psd/color.py
psd_tools/psd/vector.py
psd_tools/psd/patterns.py
psd_tools/psd/color_mode_data.py
psd_tools/psd/header.py
psd_tools/psd/bin_utils.py
psd_tools/psd/filter_effects.py
psd_tools/psd/__init__.py
psd_tools/psd/adjustments.py
psd_tools/psd/linked_layer.py
psd_tools/psd/effects_layer.py
psd_tools/psd/layer_and_mask.py
psd_tools/psd/document.py
psd_tools/psd/image_resources.py
psd_tools/psd/tagged_blocks.py
psd_tools/psd/engine_data.py
psd_tools/psd/base.py
psd_tools/composite/effects.py
psd_tools/composite/blend.py
psd_tools/composite/vector.py
psd_tools/composite/paint.py
psd_tools/composite/__init__.py
psd_tools/composite/utils.py
psd_tools/composite/composite.py
psd_tools/composite/_compat.py
psd_tools/compression/_rle.abi3.so
psd_tools/compression/__init__.py
psd_tools/compression/_rle.cpp
psd_tools/compression/rle.py
psd_tools/api/mask.py
psd_tools/api/effects.py
psd_tools/api/numpy_io.py
psd_tools/api/protocols.py
psd_tools/api/__init__.py
psd_tools/api/psd_image.py
psd_tools/api/adjustments.py
psd_tools/api/utils.py
psd_tools/api/pil_io.py
psd_tools/api/shape.py
psd_tools/api/layers.py
psd_tools/api/smart_object.py
