Metadata-Version: 2.4
Name: psd-tools
Version: 1.12.0
Summary: Python package for working with Adobe Photoshop PSD files
Author-email: Mikhail Korobov <kmike84@gmail.com>, Kota Yamaguchi <KotaYamaguchi1984@gmail.com>
License-Expression: MIT
Keywords: photoshop,psd
Classifier: Development Status :: 4 - Beta
Classifier: Intended Audience :: Developers
Classifier: Programming Language :: Python
Classifier: Programming Language :: Python :: 3
Classifier: Programming Language :: Python :: 3.10
Classifier: Programming Language :: Python :: 3.11
Classifier: Programming Language :: Python :: 3.12
Classifier: Programming Language :: Python :: 3.13
Classifier: Programming Language :: Python :: 3.14
Classifier: Topic :: Multimedia :: Graphics
Classifier: Topic :: Multimedia :: Graphics :: Viewers
Classifier: Topic :: Multimedia :: Graphics :: Graphics Conversion
Classifier: Topic :: Software Development :: Libraries :: Python Modules
Requires-Python: >=3.10
License-File: LICENSE
Requires-Dist: typing-extensions; python_version < "3.11"
Requires-Dist: attrs>=23.0.0
Requires-Dist: Pillow>=10.3.0
Requires-Dist: numpy
Provides-Extra: composite
Requires-Dist: aggdraw; extra == "composite"
Requires-Dist: scipy; extra == "composite"
Requires-Dist: scikit-image; extra == "composite"
Dynamic: license-file
